simple_appointments/__init__.py
simple_appointments/abstract_models.py
simple_appointments/admin.py
simple_appointments/apps.py
simple_appointments/conf.py
simple_appointments/forms.py
simple_appointments/mixin_forms.py
simple_appointments/mixin_models.py
simple_appointments/models.py
simple_appointments/utils.py
simple_appointments/views.py
simple_appointments/wizard_forms.py
simple_appointments/migrations/0001_initial.py
simple_appointments/migrations/__init__.py
django_simple_appointments-0.1.0.dist-info/METADATA
django_simple_appointments-0.1.0.dist-info/WHEEL
django_simple_appointments-0.1.0.dist-info/top_level.txt
django_simple_appointments-0.1.0.dist-info/RECORD
