Metadata-Version: 2.4
Name: django-simple-appointments
Version: 0.1.0
Summary: A simple reusable Django app for managing appointments
Author-email: Lucas Eduardo <lucaseduardo.s07@gmail.com>
License: MIT
Project-URL: Homepage, https://github.com/lucas-eduardo7/django-simple-appointments
Project-URL: Documentation, https://github.com/lucas-eduardo7/django-simple-appointments#readme
Classifier: Framework :: Django
Classifier: Framework :: Django :: 4.0
Classifier: Framework :: Django :: 4.1
Classifier: Framework :: Django :: 4.2
Classifier: Framework :: Django :: 5.0
Classifier: License :: OSI Approved :: MIT License
Classifier: Programming Language :: Python :: 3.10
Classifier: Programming Language :: Python :: 3.11
Classifier: Programming Language :: Python :: 3.12
Classifier: Programming Language :: Python :: 3.13
Requires-Python: >=3.10
Requires-Dist: Django>=4.0
Provides-Extra: dev
Requires-Dist: model-bakery>=1.20.5; extra == "dev"
